statline/__init__.py
statline/cli.py
statline/py.typed
statline/core/__init__.py
statline/core/calculator.py
statline/core/introspect.py
statline/core/normalization.py
statline/core/scoring.py
statline/core/weights.py
statline/core/adapters/__init__.py
statline/core/adapters/compile.py
statline/core/adapters/example.yaml
statline/core/adapters/hooks.py
statline/core/adapters/loader.py
statline/core/adapters/registry.py
statline/core/adapters/types.py
statline/core/adapters/defs/demo.yaml
statline/data/stats/dba_s0.csv
statline/data/stats/demo.csv
statline/slapi/__init__.py
statline/slapi/adapters.py
statline/slapi/app.py
statline/slapi/auth.py
statline/slapi/cache.py
statline/slapi/config.py
statline/slapi/dep.py
statline/slapi/errors.py
statline/slapi/pydantic.pyi
statline/slapi/schemas.py
statline/slapi/scoring.py
statline/slapi/storage/__init__.py
statline/slapi/storage/csv.py
statline/slapi/storage/sqlite.py
statline/slapi/storage/migrations/001_init.sql
statline/slapi/storage/migrations/002_add_indexes.sql
statline/slapi/storage/migrations/003_triggers.sql
statline/utils/logging.py
statline/utils/paths.py
statline/utils/timing.py
statline-2.0.5.dist-info/METADATA
statline-2.0.5.dist-info/WHEEL
statline-2.0.5.dist-info/entry_points.txt
statline-2.0.5.dist-info/licenses/LICENSE
statline-2.0.5.dist-info/RECORD
