Metadata-Version: 2.4
Name: statline
Version: 2.0.5
Summary: StatLine — weighted player scoring, efficiency modeling, CLI + adapter tooling
Project-URL: Homepage, https://github.com/amillolive/StatLine
Project-URL: Repository, https://github.com/amillolive/StatLine
Project-URL: Issues, https://github.com/amillolive/StatLine/issues
Project-URL: Docs, https://github.com/amillolive/StatLine#readme
Project-URL: Security, https://github.com/amillolive/StatLine/security/policy
Author: StatLine LLC
License: StatLine – Weighted Player Scoring and Analytics
License-File: LICENSE
Keywords: adapters,analytics,basketball,cli,efg,esports,google-sheets,mvp,pri,statline
Classifier: Environment :: Console
Classifier: Intended Audience :: Developers
Classifier: Intended Audience :: Science/Research
Classifier: License :: OSI Approved :: GNU Affero General Public License v3
Classifier: Programming Language :: Python :: 3
Classifier: Programming Language :: Python :: 3 :: Only
Classifier: Programming Language :: Python :: 3.10
Classifier: Programming Language :: Python :: 3.11
Classifier: Programming Language :: Python :: 3.12
Classifier: Programming Language :: Python :: 3.13
Classifier: Topic :: Scientific/Engineering :: Information Analysis
Requires-Python: <3.14,>=3.10
Requires-Dist: httpx>=0.27
Requires-Dist: pydantic<3.0,>=2.0
Requires-Dist: pyyaml>=6
Requires-Dist: typer>=0.12
Requires-Dist: typing-extensions>=4.7; python_version < '3.11'
Provides-Extra: api
Requires-Dist: fastapi<1.0,>=0.110; extra == 'api'
Requires-Dist: uvicorn[standard]>=0.30; extra == 'api'
Provides-Extra: cli
Requires-Dist: httpx>=0.27; extra == 'cli'
Requires-Dist: types-requests; (python_version < '3.14') and extra == 'cli'
Provides-Extra: cli-pretty
Requires-Dist: rich>=13.0; extra == 'cli-pretty'
Provides-Extra: dev
Requires-Dist: coverage>=7.5; extra == 'dev'
Requires-Dist: hypothesis>=6.100; extra == 'dev'
Requires-Dist: mypy>=1.11; extra == 'dev'
Requires-Dist: pytest-cov>=4.1; extra == 'dev'
Requires-Dist: pytest>=8.1; extra == 'dev'
Requires-Dist: ruff>=0.5; extra == 'dev'
Requires-Dist: types-pyyaml; extra == 'dev'
Requires-Dist: types-requests; extra == 'dev'
Provides-Extra: sheets
Requires-Dist: google-auth>=2.0.0; extra == 'sheets'
Requires-Dist: gspread>=6.0.0; extra == 'sheets'
